gmspy/__about__.py
gmspy/__init__.py
gmspy/_artif_gm.py
gmspy/_baseline_corr.py
gmspy/_const_duct_spec.py
gmspy/_elas_resp_spec.py
gmspy/_fou_pow_spec.py
gmspy/_freq_filt.py
gmspy/_lin_dyna_resp.py
gmspy/_load_gm_examples.py
gmspy/_load_peer.py
gmspy/_load_peer_batch.py
gmspy/_resample.py
gmspy/seismo.py
gmspy/test.py
gmspy/accelerograms/ChiChi.dat
gmspy/accelerograms/Friuli.dat
gmspy/accelerograms/Hollister.dat
gmspy/accelerograms/Imperial_Valley.dat
gmspy/accelerograms/Kobe.dat
gmspy/accelerograms/Kocaeli.dat
gmspy/accelerograms/Landers.dat
gmspy/accelerograms/Loma_Prieta.dat
gmspy/accelerograms/Northridge.dat
gmspy/accelerograms/Trinidad.dat
gmspy-0.1.3.dist-info/LICENCE.txt
gmspy-0.1.3.dist-info/METADATA
gmspy-0.1.3.dist-info/WHEEL
gmspy-0.1.3.dist-info/top_level.txt
gmspy-0.1.3.dist-info/RECORD
