Metadata-Version: 2.2
Name: gmspy
Version: 0.1.3
Summary: Ground Motions Signal Processing for Python
Home-page: https://github.com/yexiang1992
Author: Yexiang Yan
Author-email: yexiang_yan@outlook.com
License: GPL Licence
Keywords: Ground Motions Seismic IMs response spectra
Platform: any
Classifier: Programming Language :: Python :: 3
Requires-Python: >=3.8
License-File: LICENCE.txt
Requires-Dist: matplotlib
Requires-Dist: numpy
Requires-Dist: scipy
Requires-Dist: joblib
Requires-Dist: numba
Requires-Dist: rich
Dynamic: author
Dynamic: author-email
Dynamic: classifier
Dynamic: description
Dynamic: description-content-type
Dynamic: home-page
Dynamic: keywords
Dynamic: license
Dynamic: platform
Dynamic: requires-dist
Dynamic: requires-python
Dynamic: summary
